[
    {
        "name": "Stephanie Pierce",
        "address": "628 Ricardo Brook\nRussellchester, PA 41260",
        "email": "danadaniel@example.net",
        "phone_number": "756-618-4692",
        "job": "Pharmacologist",
        "company": "Watson Group",
        "date_of_birth": "1941-09-22",
        "ssn": "790-56-3999",
        "credit_card_number": "6544971760145161",
        "credit_card_provider": "American Express",
        "credit_card_expire": "09/28"
    },
    {
        "name": "Christopher Serrano",
        "address": "04486 Emily Trail\nMcmahonstad, MH 80855",
        "email": "udougherty@example.net",
        "phone_number": "485.280.9050x4875",
        "job": "Psychologist, clinical",
        "company": "Howard Ltd",
        "date_of_birth": "2022-09-27",
        "ssn": "224-96-4654",
        "credit_card_number": "2704238075170630",
        "credit_card_provider": "American Express",
        "credit_card_expire": "02/28"
    },
    {
        "name": "Kari Spencer",
        "address": "USS Hoffman\nFPO AE 27229",
        "email": "summerstammy@example.net",
        "phone_number": "001-772-826-3966",
        "job": "Careers adviser",
        "company": "Saunders, Lewis and Gonzales",
        "date_of_birth": "1947-07-27",
        "ssn": "032-07-2342",
        "credit_card_number": "30528683170231",
        "credit_card_provider": "VISA 16 digit",
        "credit_card_expire": "04/32"
    },
    {
        "name": "Daniel Pearson",
        "address": "8944 Jackie Mills Apt. 108\nSouth Taylor, RI 81534",
        "email": "margaretrogers@example.com",
        "phone_number": "+1-530-562-9293x8226",
        "job": "Catering manager",
        "company": "Smith, Rios and Barker",
        "date_of_birth": "1988-03-06",
        "ssn": "749-73-0506",
        "credit_card_number": "30278141954384",
        "credit_card_provider": "VISA 16 digit",
        "credit_card_expire": "02/33"
    },
    {
        "name": "Donna Oconnor",
        "address": "87166 Colleen Fort\nEast Jonathanstad, MO 34985",
        "email": "stephaniewagner@example.org",
        "phone_number": "222.842.8179x0085",
        "job": "Estate manager/land agent",
        "company": "Howard, Mclaughlin and Sanchez",
        "date_of_birth": "1962-08-19",
        "ssn": "160-87-5476",
        "credit_card_number": "30413042754761",
        "credit_card_provider": "JCB 15 digit",
        "credit_card_expire": "07/30"
    },
    {
        "name": "Heidi Garcia",
        "address": "77355 Claudia Isle\nLake Kayla, MT 93669",
        "email": "ydelgado@example.com",
        "phone_number": "535-787-6730",
        "job": "Further education lecturer",
        "company": "Chavez-French",
        "date_of_birth": "1975-10-04",
        "ssn": "894-37-4222",
        "credit_card_number": "38883283690589",
        "credit_card_provider": "VISA 16 digit",
        "credit_card_expire": "09/27"
    },
    {
        "name": "Breanna Higgins",
        "address": "1757 Huffman Wells\nSouth Chelsea, MS 47401",
        "email": "sarajones@example.com",
        "phone_number": "620-900-6988",
        "job": "Designer, graphic",
        "company": "Woodard, Stewart and Holder",
        "date_of_birth": "1968-09-26",
        "ssn": "283-93-5479",
        "credit_card_number": "4832780443652097",
        "credit_card_provider": "VISA 19 digit",
        "credit_card_expire": "05/33"
    },
    {
        "name": "Nicole Peters",
        "address": "346 Jessica Knolls\nPeggychester, AZ 41896",
        "email": "ymiles@example.org",
        "phone_number": "410.559.8553x32454",
        "job": "Food technologist",
        "company": "King, Cruz and Watts",
        "date_of_birth": "1936-04-27",
        "ssn": "199-16-2501",
        "credit_card_number": "3568256298533270",
        "credit_card_provider": "JCB 16 digit",
        "credit_card_expire": "12/30"
    },
    {
        "name": "Regina Gonzalez",
        "address": "9259 Christopher Parkway\nEdwardmouth, PW 37276",
        "email": "jennifersanchez@example.net",
        "phone_number": "539-907-6895x348",
        "job": "Energy manager",
        "company": "Murphy, Martin and Cunningham",
        "date_of_birth": "1959-02-26",
        "ssn": "718-78-2733",
        "credit_card_number": "6588316251102684",
        "credit_card_provider": "JCB 16 digit",
        "credit_card_expire": "07/30"
    },
    {
        "name": "Russell Armstrong",
        "address": "2059 Cross Hills\nBakershire, IN 96915",
        "email": "perezlevi@example.org",
        "phone_number": "(470)687-7193x94194",
        "job": "Scientist, audiological",
        "company": "Williams-Harris",
        "date_of_birth": "2024-08-25",
        "ssn": "303-47-6003",
        "credit_card_number": "4057843190447844",
        "credit_card_provider": "Diners Club / Carte Blanche",
        "credit_card_expire": "01/31"
    },
    {
        "name": "Michael Murray",
        "address": "58372 Hanson Spur Suite 670\nWest Andrewside, GA 14284",
        "email": "terrisexton@example.org",
        "phone_number": "462-417-0697x26195",
        "job": "Print production planner",
        "company": "Mendoza-Smith",
        "date_of_birth": "2020-08-13",
        "ssn": "751-09-5251",
        "credit_card_number": "36459216888129",
        "credit_card_provider": "VISA 16 digit",
        "credit_card_expire": "10/25"
    },
    {
        "name": "Victor Bruce",
        "address": "66274 Brenda Passage\nJenniferport, CO 62077",
        "email": "timothy37@example.net",
        "phone_number": "001-575-942-5897x869",
        "job": "Loss adjuster, chartered",
        "company": "Tyler, Bauer and Johnson",
        "date_of_birth": "1956-06-20",
        "ssn": "797-74-4048",
        "credit_card_number": "501856847287",
        "credit_card_provider": "VISA 19 digit",
        "credit_card_expire": "06/28"
    },
    {
        "name": "Ronald Richardson",
        "address": "937 Boone Well Suite 579\nDamonland, DC 37734",
        "email": "mcross@example.com",
        "phone_number": "001-917-264-7168x00747",
        "job": "Learning disability nurse",
        "company": "Shepard and Sons",
        "date_of_birth": "1949-06-25",
        "ssn": "018-75-1321",
        "credit_card_number": "4872484514790354",
        "credit_card_provider": "JCB 15 digit",
        "credit_card_expire": "03/33"
    },
    {
        "name": "Judith Caldwell",
        "address": "4579 Jackson Road Suite 859\nRayhaven, AZ 85690",
        "email": "robertsonbrian@example.net",
        "phone_number": "+1-549-776-5674x22625",
        "job": "Engineer, electrical",
        "company": "Cole PLC",
        "date_of_birth": "1917-06-14",
        "ssn": "541-96-3219",
        "credit_card_number": "2550036904461468",
        "credit_card_provider": "Discover",
        "credit_card_expire": "03/33"
    },
    {
        "name": "Tony Todd",
        "address": "32519 Eric Throughway\nEast Johnport, AS 94717",
        "email": "martinezjasmine@example.com",
        "phone_number": "001-963-528-9803x47814",
        "job": "Surveyor, planning and development",
        "company": "Cooper, Garcia and Forbes",
        "date_of_birth": "1937-05-11",
        "ssn": "707-03-7807",
        "credit_card_number": "3509684788924380",
        "credit_card_provider": "Maestro",
        "credit_card_expire": "10/33"
    },
    {
        "name": "Greg Willis",
        "address": "USNS Murphy\nFPO AP 05445",
        "email": "mtaylor@example.net",
        "phone_number": "(378)294-6101",
        "job": "Herbalist",
        "company": "Martin, Mitchell and Wright",
        "date_of_birth": "1983-09-18",
        "ssn": "888-75-7518",
        "credit_card_number": "4369932665022002362",
        "credit_card_provider": "JCB 16 digit",
        "credit_card_expire": "09/25"
    },
    {
        "name": "Nichole Nolan",
        "address": "479 Johnson Hill Apt. 340\nPort Jessica, GA 94356",
        "email": "kayla09@example.net",
        "phone_number": "001-992-375-6852",
        "job": "Teacher, special educational needs",
        "company": "Stokes and Sons",
        "date_of_birth": "1932-04-04",
        "ssn": "487-06-1869",
        "credit_card_number": "060409897893",
        "credit_card_provider": "Discover",
        "credit_card_expire": "08/32"
    },
    {
        "name": "Brittany Davis",
        "address": "901 Matthew Ridge Suite 634\nChandlerberg, NV 05662",
        "email": "nathangonzalez@example.org",
        "phone_number": "(646)290-3528x16392",
        "job": "Physiotherapist",
        "company": "Jackson Group",
        "date_of_birth": "1916-04-01",
        "ssn": "178-70-3107",
        "credit_card_number": "180019179264645",
        "credit_card_provider": "Maestro",
        "credit_card_expire": "10/28"
    },
    {
        "name": "Roy Morales",
        "address": "1278 Brian Pines\nEast Paulberg, VT 39066",
        "email": "simsamy@example.net",
        "phone_number": "+1-254-736-6587x4473",
        "job": "Best boy",
        "company": "Schmidt Ltd",
        "date_of_birth": "1949-03-13",
        "ssn": "567-02-2375",
        "credit_card_number": "30321143113011",
        "credit_card_provider": "JCB 16 digit",
        "credit_card_expire": "04/29"
    },
    {
        "name": "Kristin Mcbride",
        "address": "2532 Ryan Village Apt. 241\nEast Linda, DE 31852",
        "email": "jonesalexander@example.com",
        "phone_number": "586-681-5180x38253",
        "job": "Professor Emeritus",
        "company": "Ballard-Green",
        "date_of_birth": "2010-11-20",
        "ssn": "082-93-3321",
        "credit_card_number": "571096225438",
        "credit_card_provider": "VISA 13 digit",
        "credit_card_expire": "12/27"
    },
    {
        "name": "James Walker",
        "address": "088 Sophia Roads Apt. 242\nEast Nicole, LA 38398",
        "email": "matthew24@example.com",
        "phone_number": "001-206-530-3099x16278",
        "job": "Travel agency manager",
        "company": "Hall, Gonzalez and Dorsey",
        "date_of_birth": "1991-12-18",
        "ssn": "801-93-5801",
        "credit_card_number": "30285626690045",
        "credit_card_provider": "Mastercard",
        "credit_card_expire": "02/30"
    },
    {
        "name": "Marisa Jones",
        "address": "49051 Allen Plaza Suite 309\nWest Phillip, MI 93821",
        "email": "doylenicole@example.net",
        "phone_number": "+1-843-828-6769x354",
        "job": "Dramatherapist",
        "company": "Robertson, Scott and Ramirez",
        "date_of_birth": "1926-03-29",
        "ssn": "476-54-7843",
        "credit_card_number": "4748077200189212",
        "credit_card_provider": "VISA 13 digit",
        "credit_card_expire": "06/31"
    },
    {
        "name": "Sierra Reid",
        "address": "919 Ronald Squares\nAdamsfurt, VA 86607",
        "email": "stephaniesanders@example.org",
        "phone_number": "(592)751-9823x773",
        "job": "Copywriter, advertising",
        "company": "Kent, Brown and Walters",
        "date_of_birth": "2007-01-04",
        "ssn": "221-27-9108",
        "credit_card_number": "4820026696924294",
        "credit_card_provider": "JCB 15 digit",
        "credit_card_expire": "11/27"
    },
    {
        "name": "Jessica Pruitt",
        "address": "089 Rodriguez Trafficway\nWest Jill, LA 94315",
        "email": "cainangela@example.com",
        "phone_number": "513-215-4323x200",
        "job": "Youth worker",
        "company": "Villegas PLC",
        "date_of_birth": "1922-08-12",
        "ssn": "843-54-6264",
        "credit_card_number": "574114646650",
        "credit_card_provider": "JCB 15 digit",
        "credit_card_expire": "11/25"
    },
    {
        "name": "Carrie Williams",
        "address": "762 Tyler Center\nHigginsberg, SD 72157",
        "email": "williamslaura@example.net",
        "phone_number": "001-965-257-9073",
        "job": "Psychologist, counselling",
        "company": "Edwards LLC",
        "date_of_birth": "1918-09-02",
        "ssn": "458-72-1812",
        "credit_card_number": "3583853349940982",
        "credit_card_provider": "American Express",
        "credit_card_expire": "02/27"
    },
    {
        "name": "Gavin Buck",
        "address": "73692 Jonathan Flats Suite 333\nMichaelburgh, AK 52009",
        "email": "wmoore@example.net",
        "phone_number": "+1-957-383-5686",
        "job": "Fish farm manager",
        "company": "Dudley Inc",
        "date_of_birth": "2019-03-04",
        "ssn": "806-77-1391",
        "credit_card_number": "4802566644930819525",
        "credit_card_provider": "VISA 13 digit",
        "credit_card_expire": "04/32"
    },
    {
        "name": "Joshua Phillips",
        "address": "761 Baker Flat\nSheilafort, DC 23208",
        "email": "dylanbailey@example.org",
        "phone_number": "(937)850-1197x645",
        "job": "Chiropractor",
        "company": "Kidd LLC",
        "date_of_birth": "2000-07-25",
        "ssn": "131-05-1920",
        "credit_card_number": "630428364313",
        "credit_card_provider": "VISA 19 digit",
        "credit_card_expire": "05/32"
    },
    {
        "name": "Alex Ibarra",
        "address": "1016 Mitchell Ridge Apt. 814\nBenjaminville, MN 85434",
        "email": "mgonzales@example.org",
        "phone_number": "911.257.3791x11211",
        "job": "Politician's assistant",
        "company": "Bray, Bartlett and Newman",
        "date_of_birth": "1932-02-12",
        "ssn": "791-88-2184",
        "credit_card_number": "30351994722180",
        "credit_card_provider": "JCB 16 digit",
        "credit_card_expire": "03/28"
    },
    {
        "name": "Stacy Gonzales",
        "address": "86094 Leroy Mission\nNew Michaelborough, AL 66723",
        "email": "scottpierce@example.org",
        "phone_number": "8774801945",
        "job": "Public relations officer",
        "company": "Brooks-Harris",
        "date_of_birth": "1923-05-30",
        "ssn": "394-16-9277",
        "credit_card_number": "581529380353",
        "credit_card_provider": "VISA 16 digit",
        "credit_card_expire": "01/35"
    },
    {
        "name": "Ellen Carney",
        "address": "643 Gary Shoals Apt. 591\nElizabethstad, IA 48465",
        "email": "nataliethomas@example.net",
        "phone_number": "691.289.5537",
        "job": "Engineering geologist",
        "company": "Thompson-Day",
        "date_of_birth": "2019-06-03",
        "ssn": "784-65-2855",
        "credit_card_number": "4243114761137734",
        "credit_card_provider": "JCB 15 digit",
        "credit_card_expire": "08/29"
    },
    {
        "name": "Bradley Davila",
        "address": "9698 Griffin Loop Apt. 268\nSouth Lindsayborough, KS 02717",
        "email": "pattonjeffrey@example.org",
        "phone_number": "+1-787-287-3128x42389",
        "job": "Engineer, maintenance (IT)",
        "company": "Smith Inc",
        "date_of_birth": "1915-02-09",
        "ssn": "709-61-4452",
        "credit_card_number": "213163033432344",
        "credit_card_provider": "JCB 15 digit",
        "credit_card_expire": "12/29"
    },
    {
        "name": "Megan Johnson",
        "address": "83887 Natalie Row Apt. 938\nLake Jamietown, VT 60122",
        "email": "zyoung@example.com",
        "phone_number": "001-633-357-9333x749",
        "job": "Visual merchandiser",
        "company": "Jimenez, Davis and Stuart",
        "date_of_birth": "2013-09-25",
        "ssn": "200-27-7579",
        "credit_card_number": "3505842673985346",
        "credit_card_provider": "VISA 16 digit",
        "credit_card_expire": "11/25"
    },
    {
        "name": "Kayla Hill",
        "address": "74228 Richardson Valley\nJonathonstad, MO 69763",
        "email": "kenneth64@example.net",
        "phone_number": "+1-505-604-5133x8865",
        "job": "Ergonomist",
        "company": "Hawkins Inc",
        "date_of_birth": "1995-10-22",
        "ssn": "791-07-7241",
        "credit_card_number": "3574752011181175",
        "credit_card_provider": "JCB 15 digit",
        "credit_card_expire": "06/28"
    },
    {
        "name": "Robert Hobbs",
        "address": "984 Graves Lock Suite 190\nNorth Victoriaport, AS 26884",
        "email": "bjones@example.org",
        "phone_number": "+1-723-679-5593x5829",
        "job": "Make",
        "company": "Villa and Sons",
        "date_of_birth": "2005-10-29",
        "ssn": "696-21-9024",
        "credit_card_number": "4930428883749174691",
        "credit_card_provider": "JCB 15 digit",
        "credit_card_expire": "07/31"
    },
    {
        "name": "Aimee Garcia",
        "address": "17064 Williams Port\nSmithview, ID 85307",
        "email": "diane81@example.com",
        "phone_number": "3353729481",
        "job": "Conference centre manager",
        "company": "White PLC",
        "date_of_birth": "1912-12-19",
        "ssn": "421-56-9450",
        "credit_card_number": "4099857954036667442",
        "credit_card_provider": "JCB 16 digit",
        "credit_card_expire": "06/31"
    },
    {
        "name": "David Schultz",
        "address": "PSC 6756, Box 0651\nAPO AP 68148",
        "email": "kyle16@example.net",
        "phone_number": "895-952-2146",
        "job": "Nurse, adult",
        "company": "Anderson, Torres and Clark",
        "date_of_birth": "1970-03-30",
        "ssn": "675-24-3269",
        "credit_card_number": "4024038286070850844",
        "credit_card_provider": "VISA 13 digit",
        "credit_card_expire": "03/29"
    },
    {
        "name": "Victoria Stevenson",
        "address": "9420 Melissa River Apt. 819\nWest Stevenburgh, MD 76868",
        "email": "whartman@example.com",
        "phone_number": "001-988-761-7158x071",
        "job": "Scientist, research (life sciences)",
        "company": "Morgan LLC",
        "date_of_birth": "1914-03-21",
        "ssn": "559-61-6550",
        "credit_card_number": "2286436374594122",
        "credit_card_provider": "VISA 19 digit",
        "credit_card_expire": "03/34"
    },
    {
        "name": "Megan Soto",
        "address": "USNS Lee\nFPO AA 75764",
        "email": "ubaxter@example.net",
        "phone_number": "592.930.3999x279",
        "job": "International aid/development worker",
        "company": "Hernandez PLC",
        "date_of_birth": "1950-07-26",
        "ssn": "779-74-7778",
        "credit_card_number": "5219683970319504",
        "credit_card_provider": "JCB 16 digit",
        "credit_card_expire": "10/28"
    },
    {
        "name": "Tricia Watson",
        "address": "59521 Campbell Burg Suite 746\nBaldwinburgh, HI 73216",
        "email": "ifarmer@example.org",
        "phone_number": "639.698.3174",
        "job": "Facilities manager",
        "company": "Taylor Group",
        "date_of_birth": "1937-07-23",
        "ssn": "718-24-7259",
        "credit_card_number": "675945208048",
        "credit_card_provider": "JCB 16 digit",
        "credit_card_expire": "04/35"
    },
    {
        "name": "Brandi Rose",
        "address": "9683 Li Green Suite 141\nWheelerstad, NH 01347",
        "email": "hermanrichard@example.net",
        "phone_number": "(255)774-3122x92545",
        "job": "Administrator, local government",
        "company": "Hurst, Thomas and Gonzalez",
        "date_of_birth": "1982-08-26",
        "ssn": "111-30-5880",
        "credit_card_number": "344082037502575",
        "credit_card_provider": "JCB 15 digit",
        "credit_card_expire": "12/29"
    },
    {
        "name": "John Mccann Jr.",
        "address": "4022 Michael Common\nSouth Oscar, CO 80449",
        "email": "monroedaniel@example.org",
        "phone_number": "704.955.4314",
        "job": "Audiological scientist",
        "company": "Warner, Mullen and Hernandez",
        "date_of_birth": "1981-04-24",
        "ssn": "059-15-8576",
        "credit_card_number": "213160669614039",
        "credit_card_provider": "Mastercard",
        "credit_card_expire": "04/27"
    },
    {
        "name": "Rodney Burch",
        "address": "005 Jason Divide\nPort Gregorymouth, OR 21598",
        "email": "shannonmichael@example.com",
        "phone_number": "988.483.2920x35652",
        "job": "Podiatrist",
        "company": "Li-Moore",
        "date_of_birth": "1944-04-07",
        "ssn": "023-70-4116",
        "credit_card_number": "3585712275002282",
        "credit_card_provider": "JCB 16 digit",
        "credit_card_expire": "10/27"
    },
    {
        "name": "Dennis Proctor",
        "address": "92125 Harris Estates\nNew Justinton, WV 74829",
        "email": "michaelhayes@example.net",
        "phone_number": "888-931-0618",
        "job": "Designer, textile",
        "company": "Wheeler-Giles",
        "date_of_birth": "1946-07-26",
        "ssn": "086-24-8907",
        "credit_card_number": "180023819342704",
        "credit_card_provider": "American Express",
        "credit_card_expire": "08/26"
    },
    {
        "name": "Eric Welch",
        "address": "339 Hampton Fort\nJohnsonview, AZ 53060",
        "email": "bgriffith@example.com",
        "phone_number": "307.655.5577",
        "job": "Careers information officer",
        "company": "Taylor-Pennington",
        "date_of_birth": "2023-06-03",
        "ssn": "504-03-1355",
        "credit_card_number": "4665547840486888",
        "credit_card_provider": "JCB 15 digit",
        "credit_card_expire": "01/35"
    },
    {
        "name": "Stephanie Long",
        "address": "518 Mike Village\nWalkertown, NY 60715",
        "email": "julielynch@example.com",
        "phone_number": "759.569.8785",
        "job": "Surveyor, mining",
        "company": "Sanders, Wright and Mills",
        "date_of_birth": "1967-01-02",
        "ssn": "115-94-3497",
        "credit_card_number": "371208004837084",
        "credit_card_provider": "American Express",
        "credit_card_expire": "02/28"
    },
    {
        "name": "Mrs. Melinda Black",
        "address": "752 David Radial\nChristychester, MO 86922",
        "email": "ftate@example.com",
        "phone_number": "+1-230-865-9072",
        "job": "Dancer",
        "company": "Wagner PLC",
        "date_of_birth": "1965-12-06",
        "ssn": "833-18-1756",
        "credit_card_number": "213187373902509",
        "credit_card_provider": "JCB 16 digit",
        "credit_card_expire": "05/35"
    },
    {
        "name": "Vanessa Perez",
        "address": "9962 Williams Corners Suite 898\nLake Alexis, PA 62441",
        "email": "david59@example.net",
        "phone_number": "845-872-6999x928",
        "job": "Information systems manager",
        "company": "Green-Salazar",
        "date_of_birth": "1956-03-03",
        "ssn": "498-47-3740",
        "credit_card_number": "4348833910432",
        "credit_card_provider": "VISA 19 digit",
        "credit_card_expire": "03/33"
    },
    {
        "name": "Mrs. Melissa Smith MD",
        "address": "5281 Jones Dale\nLawrenceburgh, NV 89701",
        "email": "amberfrank@example.org",
        "phone_number": "001-558-374-3175x031",
        "job": "Translator",
        "company": "Gill, Avila and Price",
        "date_of_birth": "1976-06-14",
        "ssn": "891-22-8652",
        "credit_card_number": "3520118891080959",
        "credit_card_provider": "VISA 16 digit",
        "credit_card_expire": "06/30"
    },
    {
        "name": "Scott Jones",
        "address": "Unit 0508 Box 8841\nDPO AP 35041",
        "email": "hernandezpatrick@example.com",
        "phone_number": "001-638-550-9224",
        "job": "Radiographer, diagnostic",
        "company": "Landry Inc",
        "date_of_birth": "1945-10-16",
        "ssn": "161-62-1904",
        "credit_card_number": "341637719273259",
        "credit_card_provider": "VISA 16 digit",
        "credit_card_expire": "02/26"
    },
    {
        "name": "David Davis",
        "address": "52666 Kathryn Corners Apt. 457\nWilliamhaven, CA 10541",
        "email": "weberthomas@example.net",
        "phone_number": "001-298-723-6306x9926",
        "job": "Health promotion specialist",
        "company": "Norman, Ray and Pierce",
        "date_of_birth": "1916-04-28",
        "ssn": "441-17-0874",
        "credit_card_number": "3552324928175264",
        "credit_card_provider": "VISA 16 digit",
        "credit_card_expire": "08/28"
    }
]