[
    {
        "name": "Ryan Williams",
        "address": "998 Cannon Squares Apt. 348\nLake Daniel, AL 39098",
        "email": "lunasarah@example.net",
        "phone_number": "+1-296-932-0597x078",
        "job": "Writer",
        "company": "Olson-Bradshaw",
        "date_of_birth": "1934-06-24",
        "ssn": "618-44-5086",
        "credit_card_number": "2248150574647567",
        "credit_card_provider": "VISA 16 digit",
        "credit_card_expire": "07/30"
    },
    {
        "name": "Richard Ferguson",
        "address": "041 Hardin Tunnel Suite 125\nPort Elizabeth, TX 82509",
        "email": "jeffrey68@example.com",
        "phone_number": "(916)278-1046x21767",
        "job": "Chiropodist",
        "company": "Garcia, Hunter and Wilkins",
        "date_of_birth": "1959-06-05",
        "ssn": "381-57-7171",
        "credit_card_number": "213120020610480",
        "credit_card_provider": "JCB 16 digit",
        "credit_card_expire": "07/35"
    },
    {
        "name": "Jimmy Davidson",
        "address": "3724 Fox Estates\nJodiland, NY 99372",
        "email": "kevin64@example.org",
        "phone_number": "(661)433-5967x464",
        "job": "Local government officer",
        "company": "Adams, Brewer and Hernandez",
        "date_of_birth": "1935-06-26",
        "ssn": "359-97-6108",
        "credit_card_number": "501893408879",
        "credit_card_provider": "Mastercard",
        "credit_card_expire": "02/34"
    },
    {
        "name": "Derrick Love",
        "address": "5115 Boyle Ports Suite 755\nChristinechester, NY 51028",
        "email": "andrew93@example.com",
        "phone_number": "522-733-1496x31174",
        "job": "Engineer, production",
        "company": "Jordan PLC",
        "date_of_birth": "2025-09-06",
        "ssn": "816-86-0044",
        "credit_card_number": "4064667788220339556",
        "credit_card_provider": "VISA 19 digit",
        "credit_card_expire": "06/35"
    },
    {
        "name": "Peter Drake",
        "address": "6230 Sabrina Lodge Apt. 812\nPattersonfurt, AR 54548",
        "email": "mlamb@example.org",
        "phone_number": "542-739-7049x79342",
        "job": "Analytical chemist",
        "company": "Goodwin, Fox and James",
        "date_of_birth": "2016-07-11",
        "ssn": "885-97-9584",
        "credit_card_number": "3582665796901015",
        "credit_card_provider": "Diners Club / Carte Blanche",
        "credit_card_expire": "03/30"
    },
    {
        "name": "Albert Cobb",
        "address": "202 Boyd Rapids Suite 205\nNorth Ryanland, AS 87497",
        "email": "andrewslarry@example.com",
        "phone_number": "001-395-326-8973x4355",
        "job": "Historic buildings inspector/conservation officer",
        "company": "Todd-Baker",
        "date_of_birth": "1993-05-29",
        "ssn": "513-35-7862",
        "credit_card_number": "38194579720266",
        "credit_card_provider": "JCB 16 digit",
        "credit_card_expire": "01/26"
    },
    {
        "name": "Eric Fisher",
        "address": "795 Seth Course Suite 650\nTeresamouth, MT 57852",
        "email": "bpeterson@example.net",
        "phone_number": "452-388-8308",
        "job": "Radiographer, therapeutic",
        "company": "Bennett-Edwards",
        "date_of_birth": "1966-06-02",
        "ssn": "292-51-4096",
        "credit_card_number": "180067237363198",
        "credit_card_provider": "JCB 15 digit",
        "credit_card_expire": "04/30"
    },
    {
        "name": "Mitchell Walker",
        "address": "687 Rachel Isle\nCynthiatown, WA 65008",
        "email": "danielalexander@example.org",
        "phone_number": "353.774.4133x2408",
        "job": "Dietitian",
        "company": "Webster, Pratt and Lozano",
        "date_of_birth": "1932-06-07",
        "ssn": "040-25-1808",
        "credit_card_number": "6011909512167285",
        "credit_card_provider": "JCB 16 digit",
        "credit_card_expire": "05/31"
    },
    {
        "name": "Lisa Farmer",
        "address": "476 White Branch\nWest Emily, ID 79117",
        "email": "ghernandez@example.org",
        "phone_number": "(466)604-1446x9438",
        "job": "Retail merchandiser",
        "company": "Wiley-Pierce",
        "date_of_birth": "1982-06-07",
        "ssn": "244-37-6059",
        "credit_card_number": "3504710654157337",
        "credit_card_provider": "American Express",
        "credit_card_expire": "02/26"
    },
    {
        "name": "Judith Sloan",
        "address": "1321 Alicia Turnpike\nLindatown, DE 66687",
        "email": "ianwilson@example.com",
        "phone_number": "001-534-734-6971x304",
        "job": "Musician",
        "company": "Rodriguez, Harris and Gray",
        "date_of_birth": "1998-05-30",
        "ssn": "474-03-2838",
        "credit_card_number": "6011258069142311",
        "credit_card_provider": "JCB 16 digit",
        "credit_card_expire": "06/28"
    },
    {
        "name": "Catherine Anderson",
        "address": "6314 Jacqueline Course Apt. 915\nNew Alanshire, SC 54061",
        "email": "gabriel18@example.com",
        "phone_number": "001-210-287-3871x8548",
        "job": "Health physicist",
        "company": "Stewart PLC",
        "date_of_birth": "2004-03-01",
        "ssn": "145-65-8123",
        "credit_card_number": "3501480698469451",
        "credit_card_provider": "JCB 16 digit",
        "credit_card_expire": "05/34"
    },
    {
        "name": "Gregory Walker",
        "address": "5712 Flores Village\nPort Mark, RI 49738",
        "email": "christopher50@example.org",
        "phone_number": "894-327-2444",
        "job": "Teacher, special educational needs",
        "company": "Dixon-Dixon",
        "date_of_birth": "1938-07-02",
        "ssn": "890-20-9666",
        "credit_card_number": "4676772777675009",
        "credit_card_provider": "VISA 13 digit",
        "credit_card_expire": "05/26"
    },
    {
        "name": "Bailey Simmons MD",
        "address": "4777 Goodman Cove Suite 730\nEast Nicoleberg, ME 64415",
        "email": "ronniegordon@example.net",
        "phone_number": "001-797-338-8618x567",
        "job": "Advertising art director",
        "company": "Smith-Vega",
        "date_of_birth": "2001-06-05",
        "ssn": "502-92-9461",
        "credit_card_number": "3574488049798256",
        "credit_card_provider": "VISA 13 digit",
        "credit_card_expire": "09/35"
    },
    {
        "name": "Theresa Johns",
        "address": "Unit 9435 Box 8937\nDPO AA 43870",
        "email": "welchnicholas@example.org",
        "phone_number": "+1-888-421-4931x181",
        "job": "Archivist",
        "company": "Howard Ltd",
        "date_of_birth": "1937-10-17",
        "ssn": "271-78-9110",
        "credit_card_number": "30053641749307",
        "credit_card_provider": "Mastercard",
        "credit_card_expire": "10/33"
    },
    {
        "name": "Patricia Bryant",
        "address": "1578 David Terrace Apt. 760\nRyanfurt, HI 53096",
        "email": "michelle03@example.com",
        "phone_number": "(602)482-6420",
        "job": "Barrister",
        "company": "Maxwell and Sons",
        "date_of_birth": "1924-09-12",
        "ssn": "665-61-9386",
        "credit_card_number": "30429308110498",
        "credit_card_provider": "VISA 13 digit",
        "credit_card_expire": "01/30"
    },
    {
        "name": "Martin Harris",
        "address": "04437 Daniel Lane Suite 876\nNew Bradley, GA 97661",
        "email": "dustinhughes@example.org",
        "phone_number": "643.317.3123x0927",
        "job": "Chemical engineer",
        "company": "Mata Group",
        "date_of_birth": "2007-09-28",
        "ssn": "441-33-9312",
        "credit_card_number": "3545296031892912",
        "credit_card_provider": "VISA 13 digit",
        "credit_card_expire": "11/26"
    },
    {
        "name": "Peter Thomas Jr.",
        "address": "8836 Jennifer View\nWest Paulstad, NJ 85098",
        "email": "jeffrey07@example.net",
        "phone_number": "(545)687-2177",
        "job": "Communications engineer",
        "company": "Thompson, Robbins and Ross",
        "date_of_birth": "2000-10-27",
        "ssn": "062-78-5051",
        "credit_card_number": "346534427205795",
        "credit_card_provider": "American Express",
        "credit_card_expire": "11/25"
    },
    {
        "name": "James Reese",
        "address": "640 Jones Road Suite 338\nHernandezview, NM 64759",
        "email": "jamescohen@example.com",
        "phone_number": "783.425.2712x231",
        "job": "Sales promotion account executive",
        "company": "Smith PLC",
        "date_of_birth": "2007-01-20",
        "ssn": "678-59-8621",
        "credit_card_number": "347173636318237",
        "credit_card_provider": "JCB 16 digit",
        "credit_card_expire": "10/33"
    },
    {
        "name": "Jason Proctor",
        "address": "10962 Drake Crossing\nJennastad, MS 15170",
        "email": "thomaswilson@example.org",
        "phone_number": "779.662.8090",
        "job": "Police officer",
        "company": "Shaw-Lopez",
        "date_of_birth": "1974-11-17",
        "ssn": "835-80-9064",
        "credit_card_number": "4797096774579989098",
        "credit_card_provider": "VISA 16 digit",
        "credit_card_expire": "10/26"
    },
    {
        "name": "Tiffany Taylor",
        "address": "5015 Hopkins Pike\nIanburgh, CT 72190",
        "email": "greenana@example.org",
        "phone_number": "(362)418-7898x61749",
        "job": "Doctor, general practice",
        "company": "Bowers Ltd",
        "date_of_birth": "2004-03-15",
        "ssn": "338-60-8326",
        "credit_card_number": "3507854594481667",
        "credit_card_provider": "VISA 19 digit",
        "credit_card_expire": "11/34"
    },
    {
        "name": "Tyler Pearson",
        "address": "022 James Plaza\nSouth Megan, DC 35264",
        "email": "margaret16@example.org",
        "phone_number": "(617)524-0905x192",
        "job": "Medical technical officer",
        "company": "Watson-Thompson",
        "date_of_birth": "1918-08-10",
        "ssn": "491-78-3820",
        "credit_card_number": "341265350758790",
        "credit_card_provider": "VISA 19 digit",
        "credit_card_expire": "11/34"
    },
    {
        "name": "David Mcmillan",
        "address": "72527 Jeffrey Grove Suite 657\nWest Danielchester, IN 35935",
        "email": "michaelpeters@example.net",
        "phone_number": "863-771-9854",
        "job": "Medical secretary",
        "company": "Vargas, Chase and Kim",
        "date_of_birth": "2004-03-25",
        "ssn": "645-09-3940",
        "credit_card_number": "4676255913947755",
        "credit_card_provider": "Discover",
        "credit_card_expire": "02/28"
    },
    {
        "name": "Scott Johnson",
        "address": "148 Hobbs Club Suite 261\nSouth Wesleyborough, IN 02425",
        "email": "thomaswilliam@example.net",
        "phone_number": "001-416-518-0412",
        "job": "Visual merchandiser",
        "company": "Terrell-Morgan",
        "date_of_birth": "1939-07-20",
        "ssn": "456-60-6834",
        "credit_card_number": "3516907452102467",
        "credit_card_provider": "American Express",
        "credit_card_expire": "04/32"
    },
    {
        "name": "Monique Koch",
        "address": "9344 Oneal Views\nMonicafurt, MS 03018",
        "email": "arielmelton@example.com",
        "phone_number": "+1-985-449-6605x685",
        "job": "Pharmacologist",
        "company": "Hill-Gray",
        "date_of_birth": "1943-04-21",
        "ssn": "749-82-6441",
        "credit_card_number": "180035745644292",
        "credit_card_provider": "Diners Club / Carte Blanche",
        "credit_card_expire": "05/26"
    },
    {
        "name": "Kathy Cunningham",
        "address": "PSC 8349, Box 6572\nAPO AE 14490",
        "email": "bcrawford@example.net",
        "phone_number": "357.708.5045x04726",
        "job": "Education officer, museum",
        "company": "Murray, Weeks and Martinez",
        "date_of_birth": "1974-10-26",
        "ssn": "533-03-4804",
        "credit_card_number": "4848626112551970309",
        "credit_card_provider": "VISA 16 digit",
        "credit_card_expire": "12/30"
    },
    {
        "name": "Michelle Tran",
        "address": "0913 Smith Drive Suite 115\nBrianfurt, CT 56977",
        "email": "williamssara@example.net",
        "phone_number": "+1-247-430-1344x74999",
        "job": "Fashion designer",
        "company": "Bowen and Sons",
        "date_of_birth": "1998-07-13",
        "ssn": "405-14-3098",
        "credit_card_number": "4243089218498279",
        "credit_card_provider": "JCB 15 digit",
        "credit_card_expire": "03/35"
    },
    {
        "name": "Colleen Martin",
        "address": "66999 Melissa Groves Apt. 115\nBillyside, IA 17986",
        "email": "colleenmeza@example.com",
        "phone_number": "001-616-836-3166x26303",
        "job": "Adult guidance worker",
        "company": "Bush-Callahan",
        "date_of_birth": "1928-02-27",
        "ssn": "029-86-8192",
        "credit_card_number": "375890244249653",
        "credit_card_provider": "Mastercard",
        "credit_card_expire": "10/29"
    },
    {
        "name": "Alexandra Bryant",
        "address": "06088 Stacey Ridges Apt. 338\nHuertamouth, NY 79225",
        "email": "brandonbrown@example.com",
        "phone_number": "896.648.5098x25930",
        "job": "Designer, blown glass/stained glass",
        "company": "Campbell-Lang",
        "date_of_birth": "1937-05-27",
        "ssn": "156-73-0112",
        "credit_card_number": "4885967263137962",
        "credit_card_provider": "VISA 16 digit",
        "credit_card_expire": "06/33"
    },
    {
        "name": "Debra Carson",
        "address": "615 Brittany Run Apt. 631\nRobertsview, MA 58823",
        "email": "bsanders@example.net",
        "phone_number": "(381)727-8120",
        "job": "Broadcast journalist",
        "company": "Ramirez, Smith and Brown",
        "date_of_birth": "1954-12-03",
        "ssn": "344-19-0614",
        "credit_card_number": "2294294512573387",
        "credit_card_provider": "JCB 16 digit",
        "credit_card_expire": "10/28"
    },
    {
        "name": "Virginia Miller",
        "address": "1621 Thomas Burgs\nMatthewfurt, OH 64712",
        "email": "yatesjeffrey@example.net",
        "phone_number": "+1-855-468-2460",
        "job": "Economist",
        "company": "Welch-Patterson",
        "date_of_birth": "1918-11-24",
        "ssn": "096-69-7642",
        "credit_card_number": "213118968206238",
        "credit_card_provider": "American Express",
        "credit_card_expire": "06/31"
    },
    {
        "name": "Brian Fox",
        "address": "794 Thomas Alley\nSouth Ashley, LA 74911",
        "email": "maciasjoshua@example.org",
        "phone_number": "+1-827-650-6726x2941",
        "job": "Education administrator",
        "company": "Hardy Group",
        "date_of_birth": "1920-03-13",
        "ssn": "744-49-3097",
        "credit_card_number": "4482555099598189",
        "credit_card_provider": "American Express",
        "credit_card_expire": "04/35"
    },
    {
        "name": "Leslie Williams",
        "address": "7821 Allen Points\nSouth Edwardfurt, ID 64603",
        "email": "webbkristen@example.com",
        "phone_number": "334.334.8206x3895",
        "job": "Psychologist, prison and probation services",
        "company": "Garcia-Mason",
        "date_of_birth": "2017-09-12",
        "ssn": "856-44-7952",
        "credit_card_number": "3577100076873046",
        "credit_card_provider": "Diners Club / Carte Blanche",
        "credit_card_expire": "06/28"
    },
    {
        "name": "Jeremy Logan",
        "address": "63087 Sara Bridge\nColleenton, AL 48908",
        "email": "fishersarah@example.org",
        "phone_number": "001-873-969-2078x5765",
        "job": "Geologist, engineering",
        "company": "Martinez Group",
        "date_of_birth": "2017-03-05",
        "ssn": "596-81-9892",
        "credit_card_number": "4595269364573904985",
        "credit_card_provider": "JCB 16 digit",
        "credit_card_expire": "07/27"
    },
    {
        "name": "Christy Sullivan",
        "address": "4745 Autumn Club\nStanleybury, OH 46438",
        "email": "michael46@example.org",
        "phone_number": "+1-768-319-9036x23492",
        "job": "Engineer, maintenance (IT)",
        "company": "Miranda-Barrett",
        "date_of_birth": "1986-09-03",
        "ssn": "111-66-4966",
        "credit_card_number": "4345072775418861",
        "credit_card_provider": "Mastercard",
        "credit_card_expire": "07/30"
    },
    {
        "name": "Edward Williams",
        "address": "88679 Sexton Mill\nPrattborough, KS 60707",
        "email": "fruiz@example.org",
        "phone_number": "392-219-8238x71349",
        "job": "Sound technician, broadcasting/film/video",
        "company": "Garrett-Griffith",
        "date_of_birth": "1914-06-14",
        "ssn": "167-07-4963",
        "credit_card_number": "4904365337988543",
        "credit_card_provider": "VISA 16 digit",
        "credit_card_expire": "05/28"
    },
    {
        "name": "Kelli Jimenez",
        "address": "4687 Jerry Loop Apt. 134\nSouth Antonio, VI 69583",
        "email": "weaverangelica@example.net",
        "phone_number": "001-852-970-5731x511",
        "job": "Civil Service administrator",
        "company": "Charles, Snyder and Hughes",
        "date_of_birth": "2001-02-17",
        "ssn": "022-39-7650",
        "credit_card_number": "371050301793515",
        "credit_card_provider": "Mastercard",
        "credit_card_expire": "06/27"
    },
    {
        "name": "Cole Stewart",
        "address": "431 Stephen Park Apt. 809\nHeatherland, CA 38562",
        "email": "samantha18@example.com",
        "phone_number": "531.403.3969x458",
        "job": "Exhibitions officer, museum/gallery",
        "company": "Cole, Collins and Kramer",
        "date_of_birth": "2008-10-04",
        "ssn": "481-17-7704",
        "credit_card_number": "36630379339320",
        "credit_card_provider": "VISA 16 digit",
        "credit_card_expire": "07/33"
    },
    {
        "name": "Beth Lewis",
        "address": "USCGC Ochoa\nFPO AA 43461",
        "email": "john80@example.net",
        "phone_number": "+1-704-828-8549x98105",
        "job": "Education officer, museum",
        "company": "Marshall-Peters",
        "date_of_birth": "1983-12-21",
        "ssn": "787-50-5687",
        "credit_card_number": "38974187460490",
        "credit_card_provider": "VISA 16 digit",
        "credit_card_expire": "04/28"
    },
    {
        "name": "Monica Robinson",
        "address": "866 John Village Suite 134\nNorth Tristanborough, ID 69708",
        "email": "alexandercharles@example.org",
        "phone_number": "+1-839-283-6113",
        "job": "Private music teacher",
        "company": "Miller, Donovan and Marshall",
        "date_of_birth": "1914-05-21",
        "ssn": "763-36-6290",
        "credit_card_number": "4674948178526298978",
        "credit_card_provider": "VISA 13 digit",
        "credit_card_expire": "11/34"
    },
    {
        "name": "David Smith",
        "address": "315 Zachary Greens Apt. 250\nPort Brittanyport, MA 78340",
        "email": "mbrown@example.org",
        "phone_number": "531-579-1487",
        "job": "Graphic designer",
        "company": "Becker LLC",
        "date_of_birth": "1996-06-04",
        "ssn": "817-43-2928",
        "credit_card_number": "6011495411590314",
        "credit_card_provider": "JCB 15 digit",
        "credit_card_expire": "05/26"
    },
    {
        "name": "Lisa Ford",
        "address": "10543 Savannah Ville\nPowellside, WA 71212",
        "email": "grobinson@example.net",
        "phone_number": "(860)853-0929x58171",
        "job": "Software engineer",
        "company": "Yang, Bailey and Evans",
        "date_of_birth": "1952-04-25",
        "ssn": "630-26-3124",
        "credit_card_number": "4487862467052",
        "credit_card_provider": "VISA 19 digit",
        "credit_card_expire": "12/34"
    },
    {
        "name": "Spencer Coleman",
        "address": "7358 Anthony Freeway\nSanchezville, MS 73588",
        "email": "vmartinez@example.net",
        "phone_number": "001-574-222-7624",
        "job": "Energy manager",
        "company": "Wood Inc",
        "date_of_birth": "1961-04-16",
        "ssn": "723-81-6788",
        "credit_card_number": "3562244871339196",
        "credit_card_provider": "Maestro",
        "credit_card_expire": "05/32"
    },
    {
        "name": "Debbie Hancock",
        "address": "Unit 9943 Box 3152\nDPO AE 90951",
        "email": "angela19@example.net",
        "phone_number": "001-485-402-9998x4593",
        "job": "Environmental health practitioner",
        "company": "Davis Inc",
        "date_of_birth": "1912-11-22",
        "ssn": "768-23-8566",
        "credit_card_number": "30098078756408",
        "credit_card_provider": "Maestro",
        "credit_card_expire": "03/32"
    },
    {
        "name": "Joshua Washington",
        "address": "00770 Burton Mills Suite 706\nWest Stephenburgh, MH 24195",
        "email": "jchavez@example.com",
        "phone_number": "001-694-373-2629",
        "job": "Financial trader",
        "company": "Carr PLC",
        "date_of_birth": "2001-06-04",
        "ssn": "367-54-2874",
        "credit_card_number": "38552129458168",
        "credit_card_provider": "Diners Club / Carte Blanche",
        "credit_card_expire": "02/28"
    },
    {
        "name": "Brandon Mcgee",
        "address": "4108 Aaron Circle\nPort Amberton, WA 81471",
        "email": "daniel30@example.com",
        "phone_number": "787.202.2693",
        "job": "Theatre director",
        "company": "Franklin PLC",
        "date_of_birth": "1922-07-11",
        "ssn": "567-10-7527",
        "credit_card_number": "36221882131733",
        "credit_card_provider": "VISA 16 digit",
        "credit_card_expire": "10/29"
    },
    {
        "name": "Melissa Montoya",
        "address": "36655 Clark Land\nSouth Jenniferborough, FL 66328",
        "email": "millerlisa@example.com",
        "phone_number": "001-529-201-0285",
        "job": "Volunteer coordinator",
        "company": "Kaiser-Zamora",
        "date_of_birth": "1995-01-14",
        "ssn": "146-80-3994",
        "credit_card_number": "30541547738846",
        "credit_card_provider": "American Express",
        "credit_card_expire": "01/29"
    },
    {
        "name": "Kevin Adams",
        "address": "575 Beverly Islands Apt. 622\nPort Dennis, ME 78609",
        "email": "tware@example.org",
        "phone_number": "(532)450-1609x64941",
        "job": "Warehouse manager",
        "company": "Brown LLC",
        "date_of_birth": "1992-01-13",
        "ssn": "464-18-8256",
        "credit_card_number": "38064296336359",
        "credit_card_provider": "JCB 16 digit",
        "credit_card_expire": "05/31"
    },
    {
        "name": "Peter Davis",
        "address": "1568 Hawkins Forges\nMartinezburgh, MD 37703",
        "email": "treyes@example.com",
        "phone_number": "(574)384-8472",
        "job": "Pharmacist, hospital",
        "company": "Lee, Freeman and Moreno",
        "date_of_birth": "1914-12-26",
        "ssn": "532-12-9608",
        "credit_card_number": "4163525152596798",
        "credit_card_provider": "VISA 16 digit",
        "credit_card_expire": "11/31"
    },
    {
        "name": "Ralph Ramirez",
        "address": "71644 Veronica Forges Suite 571\nPatriciamouth, WY 27789",
        "email": "mayskaylee@example.com",
        "phone_number": "985-229-7546x781",
        "job": "Passenger transport manager",
        "company": "Clark-Silva",
        "date_of_birth": "1969-11-21",
        "ssn": "829-68-1212",
        "credit_card_number": "2282727195901510",
        "credit_card_provider": "JCB 16 digit",
        "credit_card_expire": "10/29"
    },
    {
        "name": "Nathaniel Jordan",
        "address": "51195 Vincent Spurs\nNorth Travisfurt, IA 35142",
        "email": "stevensscott@example.net",
        "phone_number": "955.589.6006",
        "job": "Sports development officer",
        "company": "Russell and Sons",
        "date_of_birth": "2017-12-01",
        "ssn": "179-09-2223",
        "credit_card_number": "4737517174770",
        "credit_card_provider": "VISA 16 digit",
        "credit_card_expire": "04/28"
    },
    {
        "name": "Kevin Khan",
        "address": "881 Angela Court\nJaredburgh, OK 84705",
        "email": "pduncan@example.net",
        "phone_number": "805-287-4719",
        "job": "Marine scientist",
        "company": "Davis-Johnson",
        "date_of_birth": "2003-08-21",
        "ssn": "091-03-2786",
        "credit_card_number": "6011352921067442",
        "credit_card_provider": "Maestro",
        "credit_card_expire": "06/35"
    },
    {
        "name": "Steven Jones",
        "address": "0497 Joshua Mountain Apt. 911\nNorth Deniseshire, AK 52305",
        "email": "gmcmillan@example.org",
        "phone_number": "744.436.1531x1520",
        "job": "Catering manager",
        "company": "Parks-Thompson",
        "date_of_birth": "1998-11-17",
        "ssn": "793-15-7756",
        "credit_card_number": "4769562150710",
        "credit_card_provider": "VISA 16 digit",
        "credit_card_expire": "06/28"
    },
    {
        "name": "Joshua Oliver",
        "address": "43237 Callahan Cape Apt. 046\nNorth Jordanberg, HI 19163",
        "email": "andreaharris@example.com",
        "phone_number": "001-553-284-9881x084",
        "job": "Theatre manager",
        "company": "Thompson Group",
        "date_of_birth": "2009-07-10",
        "ssn": "137-03-3430",
        "credit_card_number": "6011278410154807",
        "credit_card_provider": "VISA 13 digit",
        "credit_card_expire": "10/34"
    },
    {
        "name": "Paul Daugherty",
        "address": "58910 Sarah Pines Suite 867\nPort Todd, NM 32443",
        "email": "angelaglenn@example.com",
        "phone_number": "+1-792-442-8582",
        "job": "Surveyor, quantity",
        "company": "Henry, Jenkins and Armstrong",
        "date_of_birth": "1934-07-28",
        "ssn": "802-46-4702",
        "credit_card_number": "4280454622589721",
        "credit_card_provider": "JCB 15 digit",
        "credit_card_expire": "04/31"
    },
    {
        "name": "Thomas Russo",
        "address": "Unit 7961 Box 4487\nDPO AP 90267",
        "email": "valdezrussell@example.com",
        "phone_number": "+1-863-694-2110x25568",
        "job": "Civil engineer, contracting",
        "company": "Morgan PLC",
        "date_of_birth": "1997-06-01",
        "ssn": "672-34-1639",
        "credit_card_number": "639070723478",
        "credit_card_provider": "Mastercard",
        "credit_card_expire": "11/25"
    },
    {
        "name": "Heather Doyle MD",
        "address": "7097 Kelly Trail Apt. 208\nLake Mark, MH 48728",
        "email": "emilybentley@example.net",
        "phone_number": "(547)513-4051",
        "job": "Operations geologist",
        "company": "Benitez-Lewis",
        "date_of_birth": "2024-08-28",
        "ssn": "703-22-1457",
        "credit_card_number": "4612023879468860",
        "credit_card_provider": "VISA 16 digit",
        "credit_card_expire": "08/26"
    },
    {
        "name": "Sydney Torres",
        "address": "1588 Rubio Harbors\nVelazquezmouth, AK 25755",
        "email": "tracihuffman@example.net",
        "phone_number": "001-505-849-9360",
        "job": "Agricultural engineer",
        "company": "Martin, Horn and Burgess",
        "date_of_birth": "1997-09-17",
        "ssn": "683-64-6256",
        "credit_card_number": "2255347616364256",
        "credit_card_provider": "VISA 16 digit",
        "credit_card_expire": "04/27"
    },
    {
        "name": "Monique Walsh",
        "address": "03106 Sherry Plaza\nHowellshire, FL 57491",
        "email": "ramirezscott@example.com",
        "phone_number": "+1-980-932-3167",
        "job": "Control and instrumentation engineer",
        "company": "Martinez, Burke and Perez",
        "date_of_birth": "1918-08-04",
        "ssn": "713-08-0010",
        "credit_card_number": "4653874935944130691",
        "credit_card_provider": "Mastercard",
        "credit_card_expire": "11/29"
    },
    {
        "name": "Dr. Audrey Morgan MD",
        "address": "Unit 7366 Box 3827\nDPO AA 76069",
        "email": "craighayes@example.com",
        "phone_number": "001-558-506-6578x1858",
        "job": "Programmer, systems",
        "company": "Clayton, Wright and Jackson",
        "date_of_birth": "2006-02-27",
        "ssn": "829-27-7751",
        "credit_card_number": "4205812173673",
        "credit_card_provider": "Mastercard",
        "credit_card_expire": "05/28"
    },
    {
        "name": "Elizabeth Johnson",
        "address": "98885 James Light Suite 235\nMarymouth, GA 22137",
        "email": "nicholaswallace@example.com",
        "phone_number": "935-265-7301x5583",
        "job": "Trade mark attorney",
        "company": "Santiago-Coleman",
        "date_of_birth": "1922-11-23",
        "ssn": "422-64-4099",
        "credit_card_number": "4777315801402053",
        "credit_card_provider": "JCB 16 digit",
        "credit_card_expire": "04/28"
    },
    {
        "name": "Christie Garcia",
        "address": "609 Beth Garden Apt. 379\nMccannfort, TX 51831",
        "email": "davisjames@example.com",
        "phone_number": "(865)437-9588",
        "job": "Teacher, primary school",
        "company": "Bauer, Vasquez and Baker",
        "date_of_birth": "1980-04-27",
        "ssn": "266-49-9800",
        "credit_card_number": "6577314336342824",
        "credit_card_provider": "JCB 16 digit",
        "credit_card_expire": "09/27"
    },
    {
        "name": "Felicia Gamble",
        "address": "2813 Rhonda Crossing Suite 494\nNorth Nathan, RI 91407",
        "email": "catherine79@example.com",
        "phone_number": "+1-678-618-3433x7459",
        "job": "Chartered public finance accountant",
        "company": "Zavala, Cameron and Escobar",
        "date_of_birth": "2015-03-27",
        "ssn": "350-38-5545",
        "credit_card_number": "3505414546542272",
        "credit_card_provider": "VISA 16 digit",
        "credit_card_expire": "08/34"
    },
    {
        "name": "Regina Hall",
        "address": "0331 Jeff Canyon\nSextonport, TX 51778",
        "email": "tamimoore@example.org",
        "phone_number": "001-582-796-8264x55933",
        "job": "Research scientist (medical)",
        "company": "Ibarra-Gates",
        "date_of_birth": "1937-02-11",
        "ssn": "688-44-8364",
        "credit_card_number": "676202755622",
        "credit_card_provider": "VISA 13 digit",
        "credit_card_expire": "10/33"
    },
    {
        "name": "Melinda Cole",
        "address": "492 Kristin Parkways Apt. 119\nNew Jennifer, GU 13877",
        "email": "vlevy@example.org",
        "phone_number": "+1-538-767-4591x56989",
        "job": "Paediatric nurse",
        "company": "Butler, Davis and Martinez",
        "date_of_birth": "2005-07-13",
        "ssn": "604-43-6484",
        "credit_card_number": "180009457195538",
        "credit_card_provider": "Maestro",
        "credit_card_expire": "09/33"
    },
    {
        "name": "Laura Hansen",
        "address": "5298 Randall Radial Apt. 905\nConleyfurt, CT 82759",
        "email": "cynthiaschwartz@example.org",
        "phone_number": "001-230-799-3248x0400",
        "job": "Forensic scientist",
        "company": "Rodriguez-Francis",
        "date_of_birth": "1981-11-20",
        "ssn": "215-18-5865",
        "credit_card_number": "180029658220380",
        "credit_card_provider": "JCB 16 digit",
        "credit_card_expire": "07/29"
    },
    {
        "name": "Cynthia Garza",
        "address": "0240 Lucas Ridges Apt. 648\nDestinytown, CO 04272",
        "email": "simpsonconnor@example.net",
        "phone_number": "506.411.2014x09848",
        "job": "Osteopath",
        "company": "Soto PLC",
        "date_of_birth": "1921-11-09",
        "ssn": "706-92-8637",
        "credit_card_number": "4027249855490797",
        "credit_card_provider": "Maestro",
        "credit_card_expire": "11/34"
    },
    {
        "name": "Paul Evans",
        "address": "502 Colleen Squares\nNew Melvinport, DE 50726",
        "email": "karinadavid@example.net",
        "phone_number": "872-900-8176x6479",
        "job": "Rural practice surveyor",
        "company": "Bright, Bush and Hall",
        "date_of_birth": "1964-07-13",
        "ssn": "029-01-1865",
        "credit_card_number": "4746081942173116095",
        "credit_card_provider": "JCB 16 digit",
        "credit_card_expire": "05/31"
    },
    {
        "name": "Joseph Hatfield",
        "address": "1431 Alan Lodge\nJosephmouth, CO 81212",
        "email": "schultzjimmy@example.net",
        "phone_number": "4003811344",
        "job": "English as a second language teacher",
        "company": "Tyler PLC",
        "date_of_birth": "1931-01-19",
        "ssn": "015-39-8005",
        "credit_card_number": "4143816661046205586",
        "credit_card_provider": "Mastercard",
        "credit_card_expire": "02/33"
    },
    {
        "name": "Jason Finley",
        "address": "0669 Chavez Mall\nGreenchester, MA 09506",
        "email": "smithmaria@example.net",
        "phone_number": "2158268612",
        "job": "Teacher, adult education",
        "company": "Murphy-Chavez",
        "date_of_birth": "1924-05-11",
        "ssn": "417-02-0535",
        "credit_card_number": "30350353551438",
        "credit_card_provider": "VISA 16 digit",
        "credit_card_expire": "08/31"
    },
    {
        "name": "Holly Sellers",
        "address": "40829 Cohen Turnpike Suite 427\nPort Allisonfort, PW 62359",
        "email": "lisaweeks@example.net",
        "phone_number": "001-705-854-9624x5656",
        "job": "Ecologist",
        "company": "Davis-Mccann",
        "date_of_birth": "1964-04-29",
        "ssn": "713-76-6750",
        "credit_card_number": "4144280704059",
        "credit_card_provider": "VISA 19 digit",
        "credit_card_expire": "12/30"
    },
    {
        "name": "Betty Romero",
        "address": "776 Chris Stream Suite 097\nEast Krystalfort, MN 43435",
        "email": "davidstanley@example.org",
        "phone_number": "+1-580-546-7095x81980",
        "job": "Conference centre manager",
        "company": "Aguilar and Sons",
        "date_of_birth": "1944-09-20",
        "ssn": "568-74-6573",
        "credit_card_number": "373986780242532",
        "credit_card_provider": "JCB 16 digit",
        "credit_card_expire": "02/32"
    },
    {
        "name": "Michael Dunlap",
        "address": "90263 Smith Place Suite 026\nLake Justin, UT 80595",
        "email": "qwagner@example.org",
        "phone_number": "620.714.2534x297",
        "job": "Broadcast engineer",
        "company": "Lambert, Schroeder and Meyer",
        "date_of_birth": "1974-12-26",
        "ssn": "529-36-7429",
        "credit_card_number": "3561945184682533",
        "credit_card_provider": "Maestro",
        "credit_card_expire": "07/31"
    },
    {
        "name": "Richard Olson",
        "address": "655 Reed Overpass\nWest Tonyaview, MA 95196",
        "email": "vharris@example.net",
        "phone_number": "884.843.0458",
        "job": "Information officer",
        "company": "Bates, Miller and Tucker",
        "date_of_birth": "1997-06-20",
        "ssn": "162-25-0593",
        "credit_card_number": "576743012386",
        "credit_card_provider": "JCB 16 digit",
        "credit_card_expire": "11/28"
    },
    {
        "name": "Mr. Jeremy Thompson",
        "address": "56384 Seth Rest Apt. 241\nLake Anne, AR 13292",
        "email": "manndaniel@example.com",
        "phone_number": "+1-237-684-8382x934",
        "job": "Government social research officer",
        "company": "Gibson and Sons",
        "date_of_birth": "1966-01-09",
        "ssn": "492-35-8259",
        "credit_card_number": "3595395564088838",
        "credit_card_provider": "Diners Club / Carte Blanche",
        "credit_card_expire": "03/30"
    },
    {
        "name": "Denise Bennett",
        "address": "926 Mark Squares\nPort Donaldberg, IA 87204",
        "email": "jacob78@example.org",
        "phone_number": "237-416-5840",
        "job": "Psychologist, sport and exercise",
        "company": "Roman-Foster",
        "date_of_birth": "1947-12-18",
        "ssn": "359-76-0043",
        "credit_card_number": "3586742364779044",
        "credit_card_provider": "VISA 16 digit",
        "credit_card_expire": "02/31"
    },
    {
        "name": "Jennifer Spencer",
        "address": "5605 Brian Mountain\nJonesborough, CT 27764",
        "email": "nbell@example.com",
        "phone_number": "462.317.0138x8613",
        "job": "Veterinary surgeon",
        "company": "Miller, Hanson and Nunez",
        "date_of_birth": "1999-08-24",
        "ssn": "668-19-2633",
        "credit_card_number": "3542825946579546",
        "credit_card_provider": "Mastercard",
        "credit_card_expire": "12/34"
    },
    {
        "name": "Alicia Brown",
        "address": "1987 Shannon Freeway Apt. 387\nMartinezburgh, CT 51270",
        "email": "youngjared@example.net",
        "phone_number": "224.221.2732",
        "job": "Nurse, adult",
        "company": "Nguyen, Gilbert and Christian",
        "date_of_birth": "1963-10-29",
        "ssn": "095-30-8851",
        "credit_card_number": "4355092427936202322",
        "credit_card_provider": "American Express",
        "credit_card_expire": "07/28"
    },
    {
        "name": "Devin Elliott",
        "address": "44682 Walker Club Suite 385\nSouth David, UT 00916",
        "email": "nortonjeremy@example.org",
        "phone_number": "+1-541-645-3391x77808",
        "job": "Systems analyst",
        "company": "Kaiser-Patel",
        "date_of_birth": "1914-12-20",
        "ssn": "453-21-2589",
        "credit_card_number": "3593459021086652",
        "credit_card_provider": "Discover",
        "credit_card_expire": "05/27"
    },
    {
        "name": "Steven Sanders",
        "address": "46310 Martin Circle\nRandyshire, MP 41850",
        "email": "adrian13@example.com",
        "phone_number": "001-677-781-8106",
        "job": "Product designer",
        "company": "Hahn, Mcconnell and Davis",
        "date_of_birth": "2004-11-25",
        "ssn": "698-30-0867",
        "credit_card_number": "4251377026864",
        "credit_card_provider": "VISA 13 digit",
        "credit_card_expire": "05/33"
    },
    {
        "name": "Melvin Austin",
        "address": "52175 Sean Wells Apt. 842\nCynthiatown, NE 81845",
        "email": "andrea74@example.net",
        "phone_number": "(290)324-4391x284",
        "job": "Freight forwarder",
        "company": "Tyler, Johnson and Miller",
        "date_of_birth": "1966-10-29",
        "ssn": "802-80-2756",
        "credit_card_number": "30269263076858",
        "credit_card_provider": "Diners Club / Carte Blanche",
        "credit_card_expire": "06/35"
    },
    {
        "name": "Kelly Ross",
        "address": "44889 Mary Fields Apt. 916\nEast Brenda, OH 13017",
        "email": "mcmahondeborah@example.com",
        "phone_number": "350-907-1764",
        "job": "Charity officer",
        "company": "Jones, Wang and Lee",
        "date_of_birth": "2024-03-07",
        "ssn": "889-42-2516",
        "credit_card_number": "4663200620890661",
        "credit_card_provider": "Diners Club / Carte Blanche",
        "credit_card_expire": "12/34"
    },
    {
        "name": "Joanna Schwartz",
        "address": "42134 Spears Neck\nCalebburgh, IL 93260",
        "email": "mary17@example.org",
        "phone_number": "9795464054",
        "job": "Counsellor",
        "company": "Baxter-Murphy",
        "date_of_birth": "1920-09-28",
        "ssn": "164-95-9285",
        "credit_card_number": "4728083658049",
        "credit_card_provider": "Maestro",
        "credit_card_expire": "02/26"
    },
    {
        "name": "Eric Nguyen",
        "address": "54542 Romero Pine Suite 364\nAdamville, WV 31472",
        "email": "hbautista@example.net",
        "phone_number": "513.791.2405",
        "job": "Designer, fashion/clothing",
        "company": "Castillo Inc",
        "date_of_birth": "1913-01-19",
        "ssn": "564-74-5871",
        "credit_card_number": "6011580824159573",
        "credit_card_provider": "VISA 13 digit",
        "credit_card_expire": "02/30"
    },
    {
        "name": "Evan Johnson",
        "address": "60231 Lewis Avenue Suite 797\nLake Brianna, VA 57134",
        "email": "alexandragonzalez@example.org",
        "phone_number": "(914)382-6704",
        "job": "Physicist, medical",
        "company": "Bradford, Evans and Black",
        "date_of_birth": "2007-02-14",
        "ssn": "816-07-5572",
        "credit_card_number": "213120472683233",
        "credit_card_provider": "JCB 16 digit",
        "credit_card_expire": "07/26"
    },
    {
        "name": "Nicole Castro",
        "address": "5473 Anderson Springs\nKathleenberg, ME 16106",
        "email": "laurenhiggins@example.com",
        "phone_number": "408.292.9717x43280",
        "job": "Chiropodist",
        "company": "Cross, Morgan and Collins",
        "date_of_birth": "1970-07-21",
        "ssn": "450-97-3692",
        "credit_card_number": "372945013219890",
        "credit_card_provider": "VISA 19 digit",
        "credit_card_expire": "02/35"
    },
    {
        "name": "Jennifer Gray",
        "address": "65986 Robert Crossing Suite 826\nJessicaland, MS 54098",
        "email": "megangallagher@example.org",
        "phone_number": "668.735.0811x6353",
        "job": "Magazine features editor",
        "company": "Clarke-Yang",
        "date_of_birth": "1995-10-04",
        "ssn": "624-96-6057",
        "credit_card_number": "4897180515894683725",
        "credit_card_provider": "JCB 16 digit",
        "credit_card_expire": "06/31"
    },
    {
        "name": "Melissa Cummings",
        "address": "198 Turner Harbors Apt. 785\nNorth Mary, RI 59960",
        "email": "diana97@example.net",
        "phone_number": "846-789-0597",
        "job": "Radiographer, therapeutic",
        "company": "Clark LLC",
        "date_of_birth": "1942-09-01",
        "ssn": "451-90-7448",
        "credit_card_number": "4097832881992715",
        "credit_card_provider": "VISA 19 digit",
        "credit_card_expire": "07/32"
    },
    {
        "name": "Nicholas Townsend",
        "address": "15256 Huang Ramp Apt. 100\nAmyton, MN 92679",
        "email": "shannoncooper@example.com",
        "phone_number": "611.563.0129x355",
        "job": "Investment banker, corporate",
        "company": "Brown, Guerrero and Brown",
        "date_of_birth": "1969-05-19",
        "ssn": "002-40-0197",
        "credit_card_number": "4462426578017154",
        "credit_card_provider": "Discover",
        "credit_card_expire": "01/27"
    },
    {
        "name": "Lance Rivas",
        "address": "9541 Lewis Knoll\nFisherport, MD 54423",
        "email": "gcurtis@example.org",
        "phone_number": "(720)867-0675x8334",
        "job": "Insurance risk surveyor",
        "company": "Ellis-Diaz",
        "date_of_birth": "1947-03-17",
        "ssn": "730-32-1838",
        "credit_card_number": "6011747921766762",
        "credit_card_provider": "VISA 19 digit",
        "credit_card_expire": "06/28"
    },
    {
        "name": "Carrie Soto",
        "address": "1647 Nelson Bypass Apt. 203\nGriffithville, WA 53386",
        "email": "reyesharold@example.com",
        "phone_number": "+1-323-514-4924x546",
        "job": "Barista",
        "company": "Bates Group",
        "date_of_birth": "1975-10-15",
        "ssn": "460-77-5969",
        "credit_card_number": "213141237744532",
        "credit_card_provider": "VISA 19 digit",
        "credit_card_expire": "09/27"
    },
    {
        "name": "Elizabeth Walker",
        "address": "3420 Hansen Green\nChapmanburgh, MA 54399",
        "email": "taylorjennifer@example.org",
        "phone_number": "614.685.7561x5173",
        "job": "Designer, fashion/clothing",
        "company": "Thomas, Davis and Smith",
        "date_of_birth": "1986-03-13",
        "ssn": "358-85-8357",
        "credit_card_number": "30118483198374",
        "credit_card_provider": "VISA 19 digit",
        "credit_card_expire": "05/34"
    },
    {
        "name": "Jesus Ponce",
        "address": "Unit 0990 Box 5527\nDPO AP 58617",
        "email": "qbryant@example.net",
        "phone_number": "508-617-6757",
        "job": "Pharmacist, hospital",
        "company": "Petty-Lewis",
        "date_of_birth": "1940-04-19",
        "ssn": "615-82-0645",
        "credit_card_number": "3564755495296676",
        "credit_card_provider": "VISA 16 digit",
        "credit_card_expire": "03/28"
    },
    {
        "name": "Christopher Reyes",
        "address": "USNV Carey\nFPO AE 78762",
        "email": "bryanstephens@example.com",
        "phone_number": "(999)502-8822",
        "job": "Sports therapist",
        "company": "Bonilla Ltd",
        "date_of_birth": "2003-01-31",
        "ssn": "509-05-0133",
        "credit_card_number": "5401375077791374",
        "credit_card_provider": "American Express",
        "credit_card_expire": "07/33"
    },
    {
        "name": "Frank Taylor",
        "address": "530 Richard Station\nNormanchester, WY 97635",
        "email": "haleamy@example.com",
        "phone_number": "001-824-466-2889x6356",
        "job": "Personnel officer",
        "company": "Jackson, Roberts and Leblanc",
        "date_of_birth": "1917-12-07",
        "ssn": "048-05-8446",
        "credit_card_number": "3507609716435342",
        "credit_card_provider": "Diners Club / Carte Blanche",
        "credit_card_expire": "10/32"
    },
    {
        "name": "Sarah Hurley",
        "address": "3930 Denise Haven\nParkstown, FM 97999",
        "email": "kaitlyn47@example.com",
        "phone_number": "443-856-9112x8730",
        "job": "Conservator, museum/gallery",
        "company": "Brown Ltd",
        "date_of_birth": "1989-06-06",
        "ssn": "142-24-9816",
        "credit_card_number": "4601152706059924",
        "credit_card_provider": "VISA 19 digit",
        "credit_card_expire": "06/35"
    },
    {
        "name": "Bonnie Simmons",
        "address": "1246 Pierce Drive Apt. 919\nMichelleville, GU 10590",
        "email": "fergusonjessica@example.net",
        "phone_number": "+1-283-553-9947",
        "job": "Fashion designer",
        "company": "Prince, Smith and Elliott",
        "date_of_birth": "1936-10-02",
        "ssn": "347-46-7163",
        "credit_card_number": "213197963425233",
        "credit_card_provider": "VISA 16 digit",
        "credit_card_expire": "07/33"
    },
    {
        "name": "Amanda Ortega",
        "address": "706 Rhonda Grove\nGregstad, VT 82242",
        "email": "olee@example.net",
        "phone_number": "001-583-342-7998x47109",
        "job": "Clinical molecular geneticist",
        "company": "Fisher and Sons",
        "date_of_birth": "1936-12-01",
        "ssn": "611-23-5046",
        "credit_card_number": "676251228372",
        "credit_card_provider": "VISA 19 digit",
        "credit_card_expire": "09/30"
    },
    {
        "name": "Alicia Farmer",
        "address": "61760 Riggs Island\nKellyview, IN 41292",
        "email": "thompsondouglas@example.net",
        "phone_number": "001-888-690-6247x94204",
        "job": "Materials engineer",
        "company": "Farmer PLC",
        "date_of_birth": "2011-02-27",
        "ssn": "502-91-3834",
        "credit_card_number": "5415906142392691",
        "credit_card_provider": "Discover",
        "credit_card_expire": "08/32"
    },
    {
        "name": "Brian Caldwell",
        "address": "22798 Jon Vista\nLake Robert, AL 33497",
        "email": "vnichols@example.net",
        "phone_number": "873-814-6369",
        "job": "Engineer, civil (consulting)",
        "company": "Davis-Dillon",
        "date_of_birth": "1934-05-26",
        "ssn": "739-17-3337",
        "credit_card_number": "563328884090",
        "credit_card_provider": "Discover",
        "credit_card_expire": "03/35"
    },
    {
        "name": "Michelle Flores",
        "address": "2498 Harris Overpass\nHendersonfort, NC 40229",
        "email": "harrisaaron@example.org",
        "phone_number": "843-680-2524",
        "job": "Civil Service administrator",
        "company": "Smith, Jackson and Charles",
        "date_of_birth": "1911-01-16",
        "ssn": "691-60-2409",
        "credit_card_number": "3583973042753761",
        "credit_card_provider": "Discover",
        "credit_card_expire": "09/30"
    }
]